graphzero/__init__.py
graphzero/graphzero.cp312-win_amd64.pyd
graphzero/graphzero.pyi
graphzero-0.1.2.dist-info/METADATA
graphzero-0.1.2.dist-info/WHEEL
graphzero-0.1.2.dist-info/licenses/LICENSE
graphzero-0.1.2.dist-info/RECORD
