Metadata-Version: 2.2
Name: graphzero
Version: 0.1.2
Summary: High-performance Zero-Copy Graph Engine
Author-Email: Krish <krishsingaria2005@gmail.com>
Requires-Python: >=3.8
Requires-Dist: numpy
Requires-Dist: torch
